pybtls/simulation.py
pybtls/__init__.py
pybtls/traffic/__init__.py
pybtls/traffic/traffic_generator.py
pybtls/traffic/vehicle_generator.py
pybtls/traffic/traffic_loader.py
pybtls/traffic/headway_generator.py
pybtls/traffic/lfc.py
pybtls/post_processing/__init__.py
pybtls/bridge/influence_line.py
pybtls/bridge/bridge.py
pybtls/bridge/__init__.py
pybtls/output/output_manager.py
pybtls/output/__init__.py
pybtls/output/output_config.py
pybtls/output/plot/fatigue_rainflow.py
pybtls/output/plot/all_events.py
pybtls/output/plot/BM_summary.py
pybtls/output/plot/__init__.py
pybtls/output/plot/time_history.py
pybtls/output/plot/POT_summary.py
pybtls/output/read/fatigue_rainflow.py
pybtls/output/read/POT_vehicle.py
pybtls/output/read/all_events.py
pybtls/output/read/BM_summary.py
pybtls/output/read/__init__.py
pybtls/output/read/time_history.py
pybtls/output/read/BM_by_mixed.py
pybtls/output/read/traffic.py
pybtls/output/read/event_file.py
pybtls/output/read/fatigue_events.py
pybtls/output/read/POT_counter.py
pybtls/output/read/POT_summary.py
pybtls/output/read/E_interval_statistics.py
pybtls/output/read/BM_by_no_trucks.py
pybtls/output/read/traffic_statistics.py
pybtls/output/read/E_cumulative_statistics.py
pybtls/utils/IL_compress.py
pybtls/utils/vehicle_DF.py
pybtls/utils/output_pickle.py
pybtls/utils/__init__.py
pybtls/lib/libbtls.cpython-312-darwin.so
pybtls/lib/__init__.py
pybtls/lib/BTLS.py
pybtls/data/GraveParameters/Auxerre/AW4&5.csv
pybtls/data/GraveParameters/Auxerre/AW2&3.csv
pybtls/data/GraveParameters/Auxerre/FlowR.csv
pybtls/data/GraveParameters/Auxerre/CLASS%.csv
pybtls/data/GraveParameters/Auxerre/ATW.csv
pybtls/data/GraveParameters/Auxerre/GVWpdf.csv
pybtls/data/GraveParameters/Auxerre/HeDS.csv
pybtls/data/GraveParameters/Auxerre/ASall.csv
pybtls/data/GraveParameters/Angers/INPUT.csv
pybtls/data/GraveParameters/Angers/AW4&5.csv
pybtls/data/GraveParameters/Angers/AW2&3.csv
pybtls-1.0.1.dist-info/RECORD
pybtls-1.0.1.dist-info/WHEEL
pybtls-1.0.1.dist-info/METADATA
pybtls-1.0.1.dist-info/licenses/LICENSE
