Metadata-Version: 2.2
Name: pybtls
Version: 1.0.1
Summary: A package for short-to-mid span bridge traffic loading simulation
Keywords: bridge,traffic,simulation
Author-Email: Colin Caprani <colin.caprani@monash.edu>, Ziyi Zhou <ziyi.zhou@monash.edu>, Akbar Rizqiansyah <akbar.rizqiansyah@monash.edu>
License: GNU GPL v3
Project-URL: Documentation, https://github.com/ccaprani/btls
Project-URL: Source, https://github.com/ccaprani/btls
Project-URL: Tracker, https://github.com/ccaprani/btls/issues
Requires-Python: >=3.10
Requires-Dist: matplotlib
Requires-Dist: numpy
Requires-Dist: pandas
Requires-Dist: scipy
Provides-Extra: test
Requires-Dist: pytest>=6.0; extra == "test"
Requires-Dist: pycba>=0.5; extra == "test"
